gha_cli/__init__.py
gha_cli/cli.py
gha_cli/scanner.py
github_actions_cli-1.2.3.dist-info/METADATA
github_actions_cli-1.2.3.dist-info/WHEEL
github_actions_cli-1.2.3.dist-info/entry_points.txt
github_actions_cli-1.2.3.dist-info/licenses/LICENSE
github_actions_cli-1.2.3.dist-info/RECORD
