Metadata-Version: 2.4
Name: github-actions-cli
Version: 1.2.3
Summary: GitHub Actions CLI - allows updating workflows, etc.
Project-URL: Homepage, https://github.com/dsoftwareinc/github-actions-cli
Project-URL: Documentation, https://github.com/dsoftwareinc/github-actions-cli
Project-URL: Bug Tracker, https://github.com/dsoftwareinc/github-actions-cli/issues
Project-URL: Funding, https://github.com/sponsors/cunla
Author-email: Daniel Moran <daniel@moransoftware.ca>
Maintainer-email: Daniel Moran <daniel@moransoftware.ca>
License-Expression: BSD-3-Clause
License-File: LICENSE
Keywords: CLI,GitHub Actions
Classifier: Intended Audience :: Developers
Classifier: License :: OSI Approved :: BSD License
Classifier: Operating System :: OS Independent
Classifier: Programming Language :: Python
Classifier: Programming Language :: Python :: 3.10
Classifier: Programming Language :: Python :: 3.11
Classifier: Programming Language :: Python :: 3.12
Classifier: Programming Language :: Python :: 3.13
Classifier: Programming Language :: Python :: 3.14
Classifier: Topic :: Software Development :: Libraries :: Python Modules
Requires-Python: ~=3.10
Requires-Dist: cffi<2,>=1.17.1
Requires-Dist: click~=8.2
Requires-Dist: coloredlogs<16,>=15
Requires-Dist: pygithub~=2.6
Requires-Dist: pyyaml<7,>=6
